[
  {
    "title": "令和7年度 情報システム運用保守業務",
    "category": "it",
    "issuer_name": "厚生労働省",
    "target_area": "全国",
    "deadline": "2026-04-25",
    "budget_amount": 280000000,
    "bidding_method": "open",
    "summary": "厚生労働省が管理する情報システムの運用保守業務一式。障害対応、定期メンテナンス、ヘルプデスク運用を含む。",
    "status": "open",
    "qualification": "全省庁統一資格 A等級 役務の提供等",
    "announcement_url": "https://www.geps.go.jp/",
    "contact_info": "厚生労働省大臣官房会計課 03-5253-1111",
    "delivery_location": "東京都千代田区霞が関1-2-2",
    "has_attachment": true,
    "announcement_date": "2026-03-20",
    "contract_period": "2026年4月1日〜2027年3月31日"
  },
  {
    "title": "国道1号線舗装修繕工事（静岡地区）",
    "category": "construction",
    "issuer_name": "国土交通省 中部地方整備局",
    "target_area": "中部",
    "deadline": "2026-05-10",
    "budget_amount": 450000000,
    "bidding_method": "open",
    "summary": "国道1号線の静岡県内区間における舗装修繕工事。延長約12km、アスファルト舗装打換え及びオーバーレイ。",
    "status": "open",
    "qualification": "全省庁統一資格 土木工事 A等級",
    "announcement_url": "https://www.geps.go.jp/",
    "contact_info": "中部地方整備局 静岡国道事務所 054-xxx-xxxx",
    "delivery_location": "静岡県静岡市〜藤枝市",
    "has_attachment": true,
    "announcement_date": "2026-03-25",
    "contract_period": "2026年6月〜2026年12月"
  },
  {
    "title": "地方創生推進交付金効果検証業務",
    "category": "consulting",
    "issuer_name": "内閣府",
    "target_area": "全国",
    "deadline": "2026-04-30",
    "budget_amount": 95000000,
    "bidding_method": "proposal",
    "summary": "地方創生推進交付金の効果検証及び分析業務。全国の交付金活用事例のデータ収集、分析、報告書作成。",
    "status": "open",
    "qualification": "全省庁統一資格 役務の提供等",
    "contact_info": "内閣府地方創生推進室 03-xxxx-xxxx",
    "delivery_location": "東京都千代田区永田町",
    "announcement_date": "2026-03-15",
    "contract_period": "契約日〜2027年3月31日"
  },
  {
    "title": "消防救急デジタル無線システム整備工事",
    "category": "it",
    "issuer_name": "横浜市消防局",
    "target_area": "関東",
    "deadline": "2026-05-20",
    "budget_amount": 720000000,
    "bidding_method": "open",
    "summary": "横浜市内の消防救急デジタル無線システムの更新整備工事。基地局設備、移動局設備、指令台連接設備を含む。",
    "status": "open",
    "qualification": "電気通信工事業 特定建設業許可",
    "announcement_url": "https://www.city.yokohama.lg.jp/",
    "contact_info": "横浜市消防局総務部 045-xxx-xxxx",
    "delivery_location": "横浜市中区",
    "has_attachment": true,
    "announcement_date": "2026-04-01",
    "contract_period": "2026年7月〜2028年3月"
  },
  {
    "title": "公用車（電気自動車）購入",
    "category": "goods",
    "issuer_name": "環境省",
    "target_area": "全国",
    "deadline": "2026-04-15",
    "budget_amount": 42000000,
    "bidding_method": "open",
    "summary": "環境省本省及び地方環境事務所用の電気自動車14台の購入。充電設備の設置工事を含む。",
    "status": "open",
    "qualification": "全省庁統一資格 物品の販売",
    "contact_info": "環境省大臣官房会計課 03-xxxx-xxxx",
    "delivery_location": "環境省本省及び全国地方事務所",
    "announcement_date": "2026-03-22",
    "contract_period": "契約日〜2026年9月30日"
  },
  {
    "title": "大阪府立図書館空調設備更新工事",
    "category": "construction",
    "issuer_name": "大阪府",
    "target_area": "近畿",
    "deadline": "2026-06-05",
    "budget_amount": 185000000,
    "bidding_method": "open",
    "summary": "大阪府立中央図書館の空調設備全面更新工事。省エネ型空調機への入替え及び制御システムの更新。",
    "status": "open",
    "qualification": "管工事業 特定建設業許可 A等級",
    "announcement_url": "https://www.pref.osaka.lg.jp/",
    "contact_info": "大阪府住宅まちづくり部 06-xxxx-xxxx",
    "delivery_location": "大阪府東大阪市荒本北1-2-1",
    "has_attachment": true,
    "announcement_date": "2026-04-10",
    "contract_period": "2026年7月〜2027年2月"
  },
  {
    "title": "マイナンバーカード普及促進広報業務",
    "category": "service",
    "issuer_name": "デジタル庁",
    "target_area": "全国",
    "deadline": "2026-04-20",
    "budget_amount": 350000000,
    "bidding_method": "proposal",
    "summary": "マイナンバーカードの利活用促進に向けた広報・PR業務。テレビCM、Web広告、SNS運用、イベント企画を含む。",
    "status": "open",
    "qualification": "全省庁統一資格 役務の提供等 A等級",
    "contact_info": "デジタル庁広報戦略課 03-xxxx-xxxx",
    "delivery_location": "東京都千代田区紀尾井町1-3",
    "announcement_date": "2026-03-18",
    "contract_period": "契約日〜2027年3月31日"
  },
  {
    "title": "福岡市学校給食センター調理業務委託",
    "category": "service",
    "issuer_name": "福岡市教育委員会",
    "target_area": "九州",
    "deadline": "2026-06-30",
    "budget_amount": 520000000,
    "bidding_method": "proposal",
    "summary": "福岡市立学校給食センター（東部・西部）の調理、配送、洗浄業務の委託。年間約500万食の供給体制を維持。",
    "status": "upcoming",
    "qualification": "食品衛生法に基づく営業許可 HACCP対応",
    "contact_info": "福岡市教育委員会 学校給食課 092-xxx-xxxx",
    "delivery_location": "福岡市東区・西区",
    "announcement_date": "2026-05-01",
    "contract_period": "2026年10月〜2029年9月（3年間）"
  },
  {
    "title": "農業用水路改修工事（長野地区）",
    "category": "construction",
    "issuer_name": "農林水産省 関東農政局",
    "target_area": "中部",
    "deadline": "2026-05-25",
    "budget_amount": 230000000,
    "bidding_method": "open",
    "summary": "長野県内の農業用水路のコンクリート製開水路の改修工事。老朽化した水路の更新及び耐震補強。延長約3.5km。",
    "status": "open",
    "qualification": "全省庁統一資格 土木工事 B等級以上",
    "contact_info": "関東農政局 長野支局 026-xxx-xxxx",
    "delivery_location": "長野県松本市〜安曇野市",
    "has_attachment": true,
    "announcement_date": "2026-04-05",
    "contract_period": "2026年7月〜2027年3月"
  },
  {
    "title": "外国人技能実習機構 基幹システム開発業務",
    "category": "it",
    "issuer_name": "外国人技能実習機構",
    "target_area": "全国",
    "deadline": "2026-05-15",
    "budget_amount": 680000000,
    "bidding_method": "proposal",
    "summary": "外国人技能実習機構の基幹業務システムの再構築。申請管理、検査管理、統計分析機能のクラウド移行を含む。",
    "status": "open",
    "qualification": "ISO27001認証取得 プライバシーマーク取得",
    "announcement_url": "https://www.otit.go.jp/",
    "contact_info": "外国人技能実習機構 総務部 03-xxxx-xxxx",
    "delivery_location": "東京都港区芝浦",
    "has_attachment": true,
    "announcement_date": "2026-03-28",
    "contract_period": "2026年6月〜2028年3月"
  },
  {
    "title": "道路台帳デジタル化業務委託",
    "category": "consulting",
    "issuer_name": "名古屋市",
    "target_area": "中部",
    "deadline": "2026-05-30",
    "budget_amount": 75000000,
    "bidding_method": "proposal",
    "summary": "名古屋市管理の道路台帳（紙ベース）のデジタル化業務。GISデータへの変換、3Dモデル化を含む。",
    "status": "open",
    "qualification": "測量業者登録 GIS関連業務実績あり",
    "contact_info": "名古屋市緑政土木局 052-xxx-xxxx",
    "delivery_location": "名古屋市中区三の丸",
    "announcement_date": "2026-04-08",
    "contract_period": "契約日〜2027年3月31日"
  },
  {
    "title": "国立公園ビジターセンター展示更新業務",
    "category": "service",
    "issuer_name": "環境省 九州地方環境事務所",
    "target_area": "九州",
    "deadline": "2026-06-15",
    "budget_amount": 48000000,
    "bidding_method": "proposal",
    "summary": "阿蘇くじゅう国立公園ビジターセンターの展示物更新。多言語対応、デジタルサイネージ、VR体験コーナーの設計・施工。",
    "status": "upcoming",
    "qualification": "展示施設設計・施工実績あり",
    "contact_info": "九州地方環境事務所 096-xxx-xxxx",
    "delivery_location": "熊本県阿蘇市",
    "announcement_date": "2026-04-15",
    "contract_period": "契約日〜2027年3月31日"
  },
  {
    "title": "警察庁サイバー犯罪対策研修業務",
    "category": "service",
    "issuer_name": "警察庁",
    "target_area": "全国",
    "deadline": "2026-04-28",
    "budget_amount": 62000000,
    "bidding_method": "proposal",
    "summary": "全国の都道府県警察職員を対象としたサイバー犯罪対策の専門研修業務。オンライン・対面のハイブリッド形式。",
    "status": "open",
    "qualification": "サイバーセキュリティ研修実績 3年以上",
    "contact_info": "警察庁サイバー警察局 03-xxxx-xxxx",
    "delivery_location": "東京都千代田区霞が関2-1-2",
    "announcement_date": "2026-03-25",
    "contract_period": "2026年6月〜2027年3月"
  },
  {
    "title": "札幌市除排雪業務委託（北区）",
    "category": "service",
    "issuer_name": "札幌市",
    "target_area": "北海道",
    "deadline": "2026-07-31",
    "budget_amount": 890000000,
    "bidding_method": "open",
    "summary": "札幌市北区における冬期間の道路除排雪業務。幹線・補助幹線道路の除排雪及び凍結防止剤散布。",
    "status": "upcoming",
    "qualification": "除雪機械保有 札幌市除雪業者登録",
    "contact_info": "札幌市建設局 土木部 011-xxx-xxxx",
    "delivery_location": "札幌市北区全域",
    "announcement_date": "2026-06-01",
    "contract_period": "2026年11月〜2027年3月"
  },
  {
    "title": "税務署窓口受付システム更新業務",
    "category": "it",
    "issuer_name": "国税庁",
    "target_area": "全国",
    "deadline": "2026-05-08",
    "budget_amount": 420000000,
    "bidding_method": "open",
    "summary": "全国の税務署に設置する窓口受付番号管理システムの更新。タッチパネル端末、電光掲示板、音声案内の統合管理。",
    "status": "open",
    "qualification": "全省庁統一資格 物品の製造 A等級",
    "announcement_url": "https://www.geps.go.jp/",
    "contact_info": "国税庁長官官房会計課 03-xxxx-xxxx",
    "delivery_location": "全国524税務署",
    "has_attachment": true,
    "announcement_date": "2026-03-20",
    "contract_period": "2026年7月〜2026年12月"
  },
  {
    "title": "河川監視カメラシステム設置工事（四国地区）",
    "category": "construction",
    "issuer_name": "国土交通省 四国地方整備局",
    "target_area": "四国",
    "deadline": "2026-06-10",
    "budget_amount": 156000000,
    "bidding_method": "open",
    "summary": "四国地方の一級河川における監視カメラシステムの増設工事。AI画像解析による水位監視機能を含む。",
    "status": "open",
    "qualification": "電気工事業 建設業許可",
    "contact_info": "四国地方整備局 河川部 087-xxx-xxxx",
    "delivery_location": "香川県・徳島県・高知県・愛媛県",
    "has_attachment": true,
    "announcement_date": "2026-04-12",
    "contract_period": "2026年8月〜2027年3月"
  },
  {
    "title": "介護ロボット導入効果検証事業",
    "category": "consulting",
    "issuer_name": "厚生労働省",
    "target_area": "全国",
    "deadline": "2026-05-12",
    "budget_amount": 130000000,
    "bidding_method": "proposal",
    "summary": "介護施設における介護ロボット・ICT機器の導入効果を定量的に検証する事業。全国50施設でのフィールド調査を含む。",
    "status": "open",
    "qualification": "介護分野の調査研究実績あり",
    "contact_info": "厚生労働省老健局 03-xxxx-xxxx",
    "delivery_location": "東京都千代田区（事務局）及び全国50施設",
    "announcement_date": "2026-03-28",
    "contract_period": "契約日〜2027年3月31日"
  },
  {
    "title": "沖縄県立博物館・美術館 常設展示更新業務",
    "category": "service",
    "issuer_name": "沖縄県",
    "target_area": "沖縄",
    "deadline": "2026-06-20",
    "budget_amount": 210000000,
    "bidding_method": "proposal",
    "summary": "沖縄県立博物館・美術館の常設展示室リニューアル。映像コンテンツ制作、展示什器製作、照明設計を含む。",
    "status": "upcoming",
    "qualification": "博物館展示設計・施工実績あり",
    "contact_info": "沖縄県教育庁文化財課 098-xxx-xxxx",
    "delivery_location": "沖縄県那覇市おもろまち3-1-1",
    "announcement_date": "2026-05-01",
    "contract_period": "2026年8月〜2027年6月"
  },
  {
    "title": "東北大学 研究用高性能計算機システム調達",
    "category": "goods",
    "issuer_name": "国立大学法人東北大学",
    "target_area": "東北",
    "deadline": "2026-05-18",
    "budget_amount": 1500000000,
    "bidding_method": "open",
    "summary": "東北大学サイバーサイエンスセンターに設置する次期スーパーコンピュータシステム一式の調達。理論演算性能10PFLOPS以上。",
    "status": "open",
    "qualification": "大規模計算機システムの納入実績",
    "announcement_url": "https://www.tohoku.ac.jp/",
    "contact_info": "東北大学 財務部 022-xxx-xxxx",
    "delivery_location": "宮城県仙台市青葉区片平2-1-1",
    "has_attachment": true,
    "announcement_date": "2026-03-15",
    "contract_period": "2026年10月〜2027年3月（設置・調整期間含む）"
  },
  {
    "title": "広島市水道施設耐震診断業務",
    "category": "consulting",
    "issuer_name": "広島市水道局",
    "target_area": "中国",
    "deadline": "2026-05-22",
    "budget_amount": 55000000,
    "bidding_method": "designated",
    "summary": "広島市内の主要配水池及びポンプ場の耐震診断業務。耐震補強設計を含む。",
    "status": "open",
    "qualification": "建設コンサルタント登録 上水道部門",
    "contact_info": "広島市水道局 施設部 082-xxx-xxxx",
    "delivery_location": "広島市内各所",
    "announcement_date": "2026-04-01",
    "contract_period": "契約日〜2027年3月31日"
  }
]
